harvest/__init__.py
o2r_meta-1.1.0.dist-info/AUTHORS
o2r_meta-1.1.0.dist-info/LICENSE
o2r_meta-1.1.0.dist-info/METADATA
o2r_meta-1.1.0.dist-info/WHEEL
o2r_meta-1.1.0.dist-info/entry_points.txt
o2r_meta-1.1.0.dist-info/top_level.txt
o2r_meta-1.1.0.dist-info/RECORD
