Metadata-Version: 2.1
Name: o2r-meta
Version: 1.1.0
Summary: A package to extract metadata from files and directories
Home-page: https://github.com/o2r-project/o2r-meta
Author: o2r-project
Author-email: o2r.team@uni-muenster.de
License: MIT
Classifier: Programming Language :: Python :: 3
Classifier: License :: OSI Approved :: MIT License
Classifier: Operating System :: OS Independent
License-File: LICENSE
License-File: AUTHORS
Requires-Dist: PyYAML
Requires-Dist: dicttoxml
Requires-Dist: guess-language-spirit
Requires-Dist: jsonschema
Requires-Dist: lxml
Requires-Dist: pygeoj
Requires-Dist: python-dateutil
Requires-Dist: requests
Requires-Dist: netCDF4
Requires-Dist: StringDist
Requires-Dist: filelock
Requires-Dist: pygdal
Requires-Dist: geoextent
